wyzeapy/__init__.py
wyzeapy/const.py
wyzeapy/crypto.py
wyzeapy/exceptions.py
wyzeapy/payload_factory.py
wyzeapy/types.py
wyzeapy/utils.py
wyzeapy/wyze_auth_lib.py
wyzeapy/services/__init__.py
wyzeapy/services/base_service.py
wyzeapy/services/bulb_service.py
wyzeapy/services/camera_service.py
wyzeapy/services/hms_service.py
wyzeapy/services/irrigation_service.py
wyzeapy/services/lock_service.py
wyzeapy/services/sensor_service.py
wyzeapy/services/switch_service.py
wyzeapy/services/thermostat_service.py
wyzeapy/services/update_manager.py
wyzeapy/services/wall_switch_service.py
wyzeapy/tests/test_irrigation_service.py
wyzeapy-0.5.30.dist-info/METADATA
wyzeapy-0.5.30.dist-info/WHEEL
wyzeapy-0.5.30.dist-info/RECORD
