Metadata-Version: 2.4
Name: wyzeapy
Version: 0.5.30
Summary: A library for interacting with Wyze devices
Author-email: Katie Mulliken <katie@mulliken.net>
License: GPL-3.0-only
Requires-Python: >=3.11.0
Requires-Dist: aiodns<4.0.0,>=3.2.0
Requires-Dist: aiohttp<4.0.0,>=3.11.12
Requires-Dist: pycryptodome<4.0.0,>=3.21.0
Provides-Extra: dev
Requires-Dist: pdoc<16.0.0,>=15.0.3; extra == 'dev'
Requires-Dist: pytest<9.0.0,>=7.0.0; extra == 'dev'
